fastapi_msgspec/__init__.py
fastapi_msgspec/requests.py
fastapi_msgspec/responses.py
fastapi_msgspec/routing.py
fastapi_msgspec-0.1.0.dist-info/METADATA
fastapi_msgspec-0.1.0.dist-info/WHEEL
fastapi_msgspec-0.1.0.dist-info/licenses/LICENSE
fastapi_msgspec-0.1.0.dist-info/RECORD
